research/README.md
research/__init__.py
research/chat1.md
research/chat2.md
research/glossary.md
research/matryoshka-integration-analysis.md
research/matryoshka-research-gpt.md
research/mq64-prototype-plan.md
research/mq64-specification.md
research/voyemb.py
research/voyemb.txt
uubed_project-0.1.0.dist-info/METADATA
uubed_project-0.1.0.dist-info/WHEEL
uubed_project-0.1.0.dist-info/RECORD
