Metadata-Version: 2.4
Name: uubed-project
Version: 0.1.0
Summary: Main project hub for the uubed high-performance embedding encoding library
Project-URL: Homepage, https://github.com/twardoch/uubed
Project-URL: Repository, https://github.com/twardoch/uubed
Project-URL: Bug Tracker, https://github.com/twardoch/uubed/issues
Author: uubed contributors
License: MIT
Classifier: Development Status :: 4 - Beta
Classifier: Intended Audience :: Developers
Classifier: License :: OSI Approved :: MIT License
Classifier: Programming Language :: Python :: 3
Classifier: Programming Language :: Python :: 3.10
Classifier: Programming Language :: Python :: 3.11
Classifier: Programming Language :: Python :: 3.12
Classifier: Topic :: Scientific/Engineering :: Artificial Intelligence
Classifier: Topic :: Software Development :: Libraries :: Python Modules
Requires-Python: >=3.10
Requires-Dist: numpy>=1.20.0
Requires-Dist: rich>=10.0.0
